my_function/__init__.py
my_function/ingest_var.py
llm_package-0.2.dist-info/METADATA
llm_package-0.2.dist-info/WHEEL
llm_package-0.2.dist-info/top_level.txt
llm_package-0.2.dist-info/RECORD
