Metadata-Version: 2.1
Name: llm_package
Version: 0.2
Summary: A package containing Kubeflow Pipelines components
Home-page: https://github.com/githubuserrohith/llm_package
Author: Rohith
Author-email: your.email@example.com
License: MIT
Requires-Dist: kfp
Requires-Dist: google-cloud-storage
Requires-Dist: pandas
